qiskit_toqm/__init__.py
qiskit_toqm/toqm_latency.py
qiskit_toqm/toqm_plugin.py
qiskit_toqm/toqm_strategy.py
qiskit_toqm/toqm_strategy_presets.py
qiskit_toqm/toqm_swap.py
qiskit_toqm/native/__init__.py
qiskit_toqm/native/_core.cpython-37m-darwin.so
qiskit_toqm-0.1.0.dist-info/LICENSE
qiskit_toqm-0.1.0.dist-info/LICENSE_pybind11
qiskit_toqm-0.1.0.dist-info/METADATA
qiskit_toqm-0.1.0.dist-info/WHEEL
qiskit_toqm-0.1.0.dist-info/entry_points.txt
qiskit_toqm-0.1.0.dist-info/top_level.txt
qiskit_toqm-0.1.0.dist-info/RECORD
